pythonrc_manager/__init__.py
pythonrc_manager/py.typed
pythonrc_manager-0.1.12.dist-info/METADATA
pythonrc_manager-0.1.12.dist-info/WHEEL
pythonrc_manager-0.1.12.dist-info/licenses/LICENSE
pythonrc_manager-0.1.12.dist-info/RECORD
