Metadata-Version: 2.4
Name: pythonrc-manager
Version: 0.1.12
Summary: Utilities for Python REPL startup scripts
Author-email: Bartosz Sławecki <bartosz@ilikepython.com>
License-File: LICENSE
Requires-Python: >=3.13
